{
  "actions": [
    "buy",
    "sell"
  ],
  "fresh_days": null,
  "fresh_hours": null,
  "freshness": null,
  "generated_at": "2026-06-10T20:05:35+00:00",
  "interval": "1d",
  "limit": 50,
  "model_version": "probability-calibration-v0",
  "n_signals": 50,
  "period": "5y",
  "signals": [
    {
      "confidence": "low",
      "confirmation_lag": 1,
      "confirmed": true,
      "direction": "up",
      "end_idx": 1249,
      "end_ts": "2026-06-03 00:00:00",
      "entry_idx": 1250,
      "entry_ts": "2026-06-04 00:00:00",
      "entry_zone": "fade_after_confirmed_pattern",
      "expected_net_return": 0.06834819981118931,
      "interval": "1d",
      "lgbm_action": null,
      "lgbm_prob": null,
      "lgbm_threshold": null,
      "lookup_key": "double_corr|1d|short",
      "lookup_level": "fig_type+interval+side",
      "n_checks": 1,
      "n_errors": 0,
      "p_down": 1.0,
      "p_trade_win": 1.0,
      "p_up": 0.0,
      "pattern": "double_corr",
      "recommended_action": "sell",
      "risk_box": {
        "amplitude": 205.04000854492188,
        "entry_px": 418.9100036621094,
        "stop_px": 623.9500122070312,
        "target_px": 213.8699951171875
      },
      "sample_size": 1,
      "side": "short",
      "source_model_version": "probability-calibration-v0",
      "stop": "figure_amplitude",
      "target": "full_retrace",
      "ticker": "AVGO"
    },
    {
      "confidence": "low",
      "confirmation_lag": 3,
      "confirmed": true,
      "direction": "up",
      "end_idx": 1245,
      "end_ts": "2026-05-28 00:00:00",
      "entry_idx": 1248,
      "entry_ts": "2026-06-02 00:00:00",
      "entry_zone": "fade_after_confirmed_pattern",
      "expected_net_return": 0.04511299355282928,
      "interval": "1d",
      "lgbm_action": null,
      "lgbm_prob": null,
      "lgbm_threshold": null,
      "lookup_key": "flat|1d|short",
      "lookup_level": "fig_type+interval+side",
      "n_checks": 3,
      "n_errors": 0,
      "p_down": 0.6956521739130435,
      "p_trade_win": 0.6956521739130435,
      "p_up": 0.30434782608695654,
      "pattern": "flat",
      "recommended_action": "sell",
      "risk_box": {
        "amplitude": 273.49726467990524,
        "entry_px": 1064.1500244140625,
        "stop_px": 1337.6472890939676,
        "target_px": 790.6527597341573
      },
      "sample_size": 23,
      "side": "short",
      "source_model_version": "probability-calibration-v0",
      "stop": "figure_amplitude",
      "target": "full_retrace",
      "ticker": "LLY"
    },
    {
      "confidence": "low",
      "confirmation_lag": 1,
      "confirmed": true,
      "direction": "down",
      "end_idx": 1812,
      "end_ts": "2026-05-29 00:00:00+00:00",
      "entry_idx": 1813,
      "entry_ts": "2026-05-30 00:00:00+00:00",
      "entry_zone": "fade_after_confirmed_pattern",
      "expected_net_return": 0.021929896210771276,
      "interval": "1d",
      "lgbm_action": null,
      "lgbm_prob": null,
      "lgbm_threshold": null,
      "lookup_key": "flat|1d|long",
      "lookup_level": "fig_type+interval+side",
      "n_checks": 3,
      "n_errors": 0,
      "p_down": 0.33333333333333337,
      "p_trade_win": 0.6666666666666666,
      "p_up": 0.6666666666666666,
      "pattern": "flat",
      "recommended_action": "buy",
      "risk_box": {
        "amplitude": 0.011150000000000007,
        "entry_px": 0.09514,
        "stop_px": 0.08399,
        "target_px": 0.10629000000000001
      },
      "sample_size": 24,
      "side": "long",
      "source_model_version": "probability-calibration-v0",
      "stop": "figure_amplitude",
      "target": "full_retrace",
      "ticker": "HBAR-USD"
    },
    {
      "confidence": "low",
      "confirmation_lag": 3,
      "confirmed": true,
      "direction": "up",
      "end_idx": 1809,
      "end_ts": "2026-05-26 00:00:00+00:00",
      "entry_idx": 1812,
      "entry_ts": "2026-05-29 00:00:00+00:00",
      "entry_zone": "fade_after_confirmed_pattern",
      "expected_net_return": 0.04511299355282928,
      "interval": "1d",
      "lgbm_action": null,
      "lgbm_prob": null,
      "lgbm_threshold": null,
      "lookup_key": "flat|1d|short",
      "lookup_level": "fig_type+interval+side",
      "n_checks": 3,
      "n_errors": 0,
      "p_down": 0.6956521739130435,
      "p_trade_win": 0.6956521739130435,
      "p_up": 0.30434782608695654,
      "pattern": "flat",
      "recommended_action": "sell",
      "risk_box": {
        "amplitude": 0.45999999999999996,
        "entry_px": 2.017,
        "stop_px": 2.477,
        "target_px": 1.557
      },
      "sample_size": 23,
      "side": "short",
      "source_model_version": "probability-calibration-v0",
      "stop": "figure_amplitude",
      "target": "full_retrace",
      "ticker": "ATOM-USD"
    },
    {
      "confidence": "low",
      "confirmation_lag": 10,
      "confirmed": true,
      "direction": "down",
      "end_idx": 1800,
      "end_ts": "2026-05-17 00:00:00+00:00",
      "entry_idx": 1810,
      "entry_ts": "2026-05-27 00:00:00+00:00",
      "entry_zone": "fade_after_confirmed_pattern",
      "expected_net_return": 0.021929896210771276,
      "interval": "1d",
      "lgbm_action": null,
      "lgbm_prob": null,
      "lgbm_threshold": null,
      "lookup_key": "flat|1d|long",
      "lookup_level": "fig_type+interval+side",
      "n_checks": 3,
      "n_errors": 0,
      "p_down": 0.33333333333333337,
      "p_trade_win": 0.6666666666666666,
      "p_up": 0.6666666666666666,
      "pattern": "flat",
      "recommended_action": "buy",
      "risk_box": {
        "amplitude": 0.41600000000000004,
        "entry_px": 1.031,
        "stop_px": 0.6149999999999999,
        "target_px": 1.447
      },
      "sample_size": 24,
      "side": "long",
      "source_model_version": "probability-calibration-v0",
      "stop": "figure_amplitude",
      "target": "full_retrace",
      "ticker": "FIL-USD"
    },
    {
      "confidence": "low",
      "confirmation_lag": 6,
      "confirmed": true,
      "direction": "up",
      "end_idx": 1793,
      "end_ts": "2026-05-10 00:00:00+00:00",
      "entry_idx": 1799,
      "entry_ts": "2026-05-16 00:00:00+00:00",
      "entry_zone": "fade_after_confirmed_pattern",
      "expected_net_return": 0.06834819981118931,
      "interval": "1d",
      "lgbm_action": null,
      "lgbm_prob": null,
      "lgbm_threshold": null,
      "lookup_key": "double_corr|1d|short",
      "lookup_level": "fig_type+interval+side",
      "n_checks": 1,
      "n_errors": 0,
      "p_down": 1.0,
      "p_trade_win": 1.0,
      "p_up": 0.0,
      "pattern": "double_corr",
      "recommended_action": "sell",
      "risk_box": {
        "amplitude": 15.54,
        "entry_px": 56.14,
        "stop_px": 71.68,
        "target_px": 40.6
      },
      "sample_size": 1,
      "side": "short",
      "source_model_version": "probability-calibration-v0",
      "stop": "figure_amplitude",
      "target": "full_retrace",
      "ticker": "LTC-USD"
    },
    {
      "confidence": "low",
      "confirmation_lag": 2,
      "confirmed": true,
      "direction": "down",
      "end_idx": 1204,
      "end_ts": "2026-03-30 00:00:00",
      "entry_idx": 1206,
      "entry_ts": "2026-04-01 00:00:00",
      "entry_zone": "fade_after_confirmed_pattern",
      "expected_net_return": 0.021929896210771276,
      "interval": "1d",
      "lgbm_action": null,
      "lgbm_prob": null,
      "lgbm_threshold": null,
      "lookup_key": "flat|1d|long",
      "lookup_level": "fig_type+interval+side",
      "n_checks": 3,
      "n_errors": 0,
      "p_down": 0.33333333333333337,
      "p_trade_win": 0.6666666666666666,
      "p_up": 0.6666666666666666,
      "pattern": "flat",
      "recommended_action": "buy",
      "risk_box": {
        "amplitude": 65.13224187795959,
        "entry_px": 341.489990234375,
        "stop_px": 276.3577483564154,
        "target_px": 406.6222321123346
      },
      "sample_size": 24,
      "side": "long",
      "source_model_version": "probability-calibration-v0",
      "stop": "figure_amplitude",
      "target": "full_retrace",
      "ticker": "TSM"
    },
    {
      "confidence": "low",
      "confirmation_lag": 2,
      "confirmed": true,
      "direction": "down",
      "end_idx": 1204,
      "end_ts": "2026-03-30 00:00:00",
      "entry_idx": 1206,
      "entry_ts": "2026-04-01 00:00:00",
      "entry_zone": "fade_after_confirmed_pattern",
      "expected_net_return": 0.021929896210771276,
      "interval": "1d",
      "lgbm_action": null,
      "lgbm_prob": null,
      "lgbm_threshold": null,
      "lookup_key": "flat|1d|long",
      "lookup_level": "fig_type+interval+side",
      "n_checks": 3,
      "n_errors": 0,
      "p_down": 0.33333333333333337,
      "p_trade_win": 0.6666666666666666,
      "p_up": 0.6666666666666666,
      "pattern": "flat",
      "recommended_action": "buy",
      "risk_box": {
        "amplitude": 68.09980048786156,
        "entry_px": 297.2124938964844,
        "stop_px": 229.11269340862282,
        "target_px": 365.31229438434593
      },
      "sample_size": 24,
      "side": "long",
      "source_model_version": "probability-calibration-v0",
      "stop": "figure_amplitude",
      "target": "full_retrace",
      "ticker": "GOOGL"
    },
    {
      "confidence": "low",
      "confirmation_lag": 3,
      "confirmed": true,
      "direction": "up",
      "end_idx": 614,
      "end_ts": "2026-02-26 00:00:00",
      "entry_idx": 617,
      "entry_ts": "2026-03-03 00:00:00",
      "entry_zone": "fade_after_confirmed_pattern",
      "expected_net_return": 0.04511299355282928,
      "interval": "1d",
      "lgbm_action": null,
      "lgbm_prob": null,
      "lgbm_threshold": null,
      "lookup_key": "flat|1d|short",
      "lookup_level": "fig_type+interval+side",
      "n_checks": 3,
      "n_errors": 0,
      "p_down": 0.6956521739130435,
      "p_trade_win": 0.6956521739130435,
      "p_up": 0.30434782608695654,
      "pattern": "flat",
      "recommended_action": "sell",
      "risk_box": {
        "amplitude": 32.23999786376953,
        "entry_px": 121.72000122070312,
        "stop_px": 153.95999908447266,
        "target_px": 89.4800033569336
      },
      "sample_size": 23,
      "side": "short",
      "source_model_version": "probability-calibration-v0",
      "stop": "figure_amplitude",
      "target": "full_retrace",
      "ticker": "ARM"
    },
    {
      "confidence": "low",
      "confirmation_lag": 3,
      "confirmed": true,
      "direction": "down",
      "end_idx": 1168,
      "end_ts": "2026-02-05 00:00:00",
      "entry_idx": 1171,
      "entry_ts": "2026-02-10 00:00:00",
      "entry_zone": "fade_after_confirmed_pattern",
      "expected_net_return": 0.021929896210771276,
      "interval": "1d",
      "lgbm_action": null,
      "lgbm_prob": null,
      "lgbm_threshold": null,
      "lookup_key": "flat|1d|long",
      "lookup_level": "fig_type+interval+side",
      "n_checks": 3,
      "n_errors": 0,
      "p_down": 0.33333333333333337,
      "p_trade_win": 0.6666666666666666,
      "p_up": 0.6666666666666666,
      "pattern": "flat",
      "recommended_action": "buy",
      "risk_box": {
        "amplitude": 86.54000854492188,
        "entry_px": 425.2099914550781,
        "stop_px": 338.66998291015625,
        "target_px": 511.75
      },
      "sample_size": 24,
      "side": "long",
      "source_model_version": "probability-calibration-v0",
      "stop": "figure_amplitude",
      "target": "full_retrace",
      "ticker": "TSLA"
    },
    {
      "confidence": "low",
      "confirmation_lag": 0,
      "confirmed": true,
      "direction": "up",
      "end_idx": 1322,
      "end_ts": "2026-01-13 00:00:00+00:00",
      "entry_idx": 1322,
      "entry_ts": "2026-01-13 00:00:00+00:00",
      "entry_zone": "fade_after_confirmed_pattern",
      "expected_net_return": 0.04511299355282928,
      "interval": "1d",
      "lgbm_action": null,
      "lgbm_prob": null,
      "lgbm_threshold": null,
      "lookup_key": "flat|1d|short",
      "lookup_level": "fig_type+interval+side",
      "n_checks": 3,
      "n_errors": 0,
      "p_down": 0.6956521739130435,
      "p_trade_win": 0.6956521739130435,
      "p_up": 0.30434782608695654,
      "pattern": "flat",
      "recommended_action": "sell",
      "risk_box": {
        "amplitude": 0.05870000000000003,
        "entry_px": 0.3669,
        "stop_px": 0.42560000000000003,
        "target_px": 0.3082
      },
      "sample_size": 23,
      "side": "short",
      "source_model_version": "probability-calibration-v0",
      "stop": "figure_amplitude",
      "target": "full_retrace",
      "ticker": "OP-USD"
    },
    {
      "confidence": "low",
      "confirmation_lag": 10,
      "confirmed": true,
      "direction": "down",
      "end_idx": 1135,
      "end_ts": "2025-12-17 00:00:00",
      "entry_idx": 1145,
      "entry_ts": "2026-01-02 00:00:00",
      "entry_zone": "fade_after_confirmed_pattern",
      "expected_net_return": 0.021929896210771276,
      "interval": "1d",
      "lgbm_action": null,
      "lgbm_prob": null,
      "lgbm_threshold": null,
      "lookup_key": "flat|1d|long",
      "lookup_level": "fig_type+interval+side",
      "n_checks": 3,
      "n_errors": 0,
      "p_down": 0.33333333333333337,
      "p_trade_win": 0.6666666666666666,
      "p_up": 0.6666666666666666,
      "pattern": "flat",
      "recommended_action": "buy",
      "risk_box": {
        "amplitude": 54.44137350858489,
        "entry_px": 346.8923034667969,
        "stop_px": 292.450929958212,
        "target_px": 401.33367697538176
      },
      "sample_size": 24,
      "side": "long",
      "source_model_version": "probability-calibration-v0",
      "stop": "figure_amplitude",
      "target": "full_retrace",
      "ticker": "AVGO"
    },
    {
      "confidence": "low",
      "confirmation_lag": 5,
      "confirmed": true,
      "direction": "up",
      "end_idx": 1128,
      "end_ts": "2025-12-08 00:00:00",
      "entry_idx": 1133,
      "entry_ts": "2025-12-15 00:00:00",
      "entry_zone": "fade_after_confirmed_pattern",
      "expected_net_return": 0.04511299355282928,
      "interval": "1d",
      "lgbm_action": null,
      "lgbm_prob": null,
      "lgbm_threshold": null,
      "lookup_key": "flat|1d|short",
      "lookup_level": "fig_type+interval+side",
      "n_checks": 3,
      "n_errors": 0,
      "p_down": 0.6956521739130435,
      "p_trade_win": 0.6956521739130435,
      "p_up": 0.30434782608695654,
      "pattern": "flat",
      "recommended_action": "sell",
      "risk_box": {
        "amplitude": 16.699996948242188,
        "entry_px": 185.8800048828125,
        "stop_px": 202.5800018310547,
        "target_px": 169.1800079345703
      },
      "sample_size": 23,
      "side": "short",
      "source_model_version": "probability-calibration-v0",
      "stop": "figure_amplitude",
      "target": "full_retrace",
      "ticker": "PANW"
    },
    {
      "confidence": "low",
      "confirmation_lag": 9,
      "confirmed": true,
      "direction": "down",
      "end_idx": 1118,
      "end_ts": "2025-11-21 00:00:00",
      "entry_idx": 1127,
      "entry_ts": "2025-12-05 00:00:00",
      "entry_zone": "fade_after_confirmed_pattern",
      "expected_net_return": 0.021929896210771276,
      "interval": "1d",
      "lgbm_action": null,
      "lgbm_prob": null,
      "lgbm_threshold": null,
      "lookup_key": "flat|1d|long",
      "lookup_level": "fig_type+interval+side",
      "n_checks": 3,
      "n_errors": 0,
      "p_down": 0.33333333333333337,
      "p_trade_win": 0.6666666666666666,
      "p_up": 0.6666666666666666,
      "pattern": "flat",
      "recommended_action": "buy",
      "risk_box": {
        "amplitude": 39.8599853515625,
        "entry_px": 512.030029296875,
        "stop_px": 472.1700439453125,
        "target_px": 551.8900146484375
      },
      "sample_size": 24,
      "side": "long",
      "source_model_version": "probability-calibration-v0",
      "stop": "figure_amplitude",
      "target": "full_retrace",
      "ticker": "CRWD"
    },
    {
      "confidence": "low",
      "confirmation_lag": 6,
      "confirmed": true,
      "direction": "down",
      "end_idx": 1120,
      "end_ts": "2025-11-25 00:00:00",
      "entry_idx": 1126,
      "entry_ts": "2025-12-04 00:00:00",
      "entry_zone": "fade_after_confirmed_pattern",
      "expected_net_return": 0.021929896210771276,
      "interval": "1d",
      "lgbm_action": null,
      "lgbm_prob": null,
      "lgbm_threshold": null,
      "lookup_key": "flat|1d|long",
      "lookup_level": "fig_type+interval+side",
      "n_checks": 3,
      "n_errors": 0,
      "p_down": 0.33333333333333337,
      "p_trade_win": 0.6666666666666666,
      "p_up": 0.6666666666666666,
      "pattern": "flat",
      "recommended_action": "buy",
      "risk_box": {
        "amplitude": 158.51696557298237,
        "entry_px": 213.0209503173828,
        "stop_px": 54.50398474440044,
        "target_px": 371.5379158903652
      },
      "sample_size": 24,
      "side": "long",
      "source_model_version": "probability-calibration-v0",
      "stop": "figure_amplitude",
      "target": "full_retrace",
      "ticker": "ORCL"
    },
    {
      "confidence": "low",
      "confirmation_lag": 6,
      "confirmed": true,
      "direction": "down",
      "end_idx": 1118,
      "end_ts": "2025-11-21 00:00:00",
      "entry_idx": 1124,
      "entry_ts": "2025-12-02 00:00:00",
      "entry_zone": "fade_after_confirmed_pattern",
      "expected_net_return": 0.021929896210771276,
      "interval": "1d",
      "lgbm_action": null,
      "lgbm_prob": null,
      "lgbm_threshold": null,
      "lookup_key": "flat|1d|long",
      "lookup_level": "fig_type+interval+side",
      "n_checks": 3,
      "n_errors": 0,
      "p_down": 0.33333333333333337,
      "p_trade_win": 0.6666666666666666,
      "p_up": 0.6666666666666666,
      "pattern": "flat",
      "recommended_action": "buy",
      "risk_box": {
        "amplitude": 6.321785942859378,
        "entry_px": 580.006103515625,
        "stop_px": 573.6843175727656,
        "target_px": 586.3278894584844
      },
      "sample_size": 24,
      "side": "long",
      "source_model_version": "probability-calibration-v0",
      "stop": "figure_amplitude",
      "target": "full_retrace",
      "ticker": "CAT"
    },
    {
      "confidence": "low",
      "confirmation_lag": 3,
      "confirmed": true,
      "direction": "down",
      "end_idx": 1118,
      "end_ts": "2025-11-21 00:00:00",
      "entry_idx": 1121,
      "entry_ts": "2025-11-26 00:00:00",
      "entry_zone": "fade_after_confirmed_pattern",
      "expected_net_return": 0.021929896210771276,
      "interval": "1d",
      "lgbm_action": null,
      "lgbm_prob": null,
      "lgbm_threshold": null,
      "lookup_key": "flat|1d|long",
      "lookup_level": "fig_type+interval+side",
      "n_checks": 3,
      "n_errors": 0,
      "p_down": 0.33333333333333337,
      "p_trade_win": 0.6666666666666666,
      "p_up": 0.6666666666666666,
      "pattern": "flat",
      "recommended_action": "buy",
      "risk_box": {
        "amplitude": 44.30521873266275,
        "entry_px": 288.36676025390625,
        "stop_px": 244.0615415212435,
        "target_px": 332.671978986569
      },
      "sample_size": 24,
      "side": "long",
      "source_model_version": "probability-calibration-v0",
      "stop": "figure_amplitude",
      "target": "full_retrace",
      "ticker": "TSM"
    },
    {
      "confidence": "low",
      "confirmation_lag": 3,
      "confirmed": true,
      "direction": "down",
      "end_idx": 1118,
      "end_ts": "2025-11-21 00:00:00",
      "entry_idx": 1121,
      "entry_ts": "2025-11-26 00:00:00",
      "entry_zone": "fade_after_confirmed_pattern",
      "expected_net_return": 0.021929896210771276,
      "interval": "1d",
      "lgbm_action": null,
      "lgbm_prob": null,
      "lgbm_threshold": null,
      "lookup_key": "flat|1d|long",
      "lookup_level": "fig_type+interval+side",
      "n_checks": 3,
      "n_errors": 0,
      "p_down": 0.33333333333333337,
      "p_trade_win": 0.6666666666666666,
      "p_up": 0.6666666666666666,
      "pattern": "flat",
      "recommended_action": "buy",
      "risk_box": {
        "amplitude": 8.403081204848547,
        "entry_px": 230.0703582763672,
        "stop_px": 221.66727707151864,
        "target_px": 238.47343948121573
      },
      "sample_size": 24,
      "side": "long",
      "source_model_version": "probability-calibration-v0",
      "stop": "figure_amplitude",
      "target": "full_retrace",
      "ticker": "MU"
    },
    {
      "confidence": "low",
      "confirmation_lag": 8,
      "confirmed": true,
      "direction": "up",
      "end_idx": 1611,
      "end_ts": "2025-11-09 00:00:00+00:00",
      "entry_idx": 1619,
      "entry_ts": "2025-11-17 00:00:00+00:00",
      "entry_zone": "fade_after_confirmed_pattern",
      "expected_net_return": 0.06834819981118931,
      "interval": "1d",
      "lgbm_action": null,
      "lgbm_prob": null,
      "lgbm_threshold": null,
      "lookup_key": "double_corr|1d|short",
      "lookup_level": "fig_type+interval+side",
      "n_checks": 1,
      "n_errors": 0,
      "p_down": 1.0,
      "p_trade_win": 1.0,
      "p_up": 0.0,
      "pattern": "double_corr",
      "recommended_action": "sell",
      "risk_box": {
        "amplitude": 60.99999999999999,
        "entry_px": 91.24,
        "stop_px": 152.23999999999998,
        "target_px": 30.240000000000002
      },
      "sample_size": 1,
      "side": "short",
      "source_model_version": "probability-calibration-v0",
      "stop": "figure_amplitude",
      "target": "full_retrace",
      "ticker": "LTC-USD"
    },
    {
      "confidence": "low",
      "confirmation_lag": 6,
      "confirmed": true,
      "direction": "up",
      "end_idx": 531,
      "end_ts": "2025-10-27 00:00:00",
      "entry_idx": 537,
      "entry_ts": "2025-11-04 00:00:00",
      "entry_zone": "fade_after_confirmed_pattern",
      "expected_net_return": 0.06834819981118931,
      "interval": "1d",
      "lgbm_action": null,
      "lgbm_prob": null,
      "lgbm_threshold": null,
      "lookup_key": "double_corr|1d|short",
      "lookup_level": "fig_type+interval+side",
      "n_checks": 1,
      "n_errors": 0,
      "p_down": 1.0,
      "p_trade_win": 1.0,
      "p_up": 0.0,
      "pattern": "double_corr",
      "recommended_action": "sell",
      "risk_box": {
        "amplitude": 45.540008544921875,
        "entry_px": 160.72999572753906,
        "stop_px": 206.27000427246094,
        "target_px": 115.18998718261719
      },
      "sample_size": 1,
      "side": "short",
      "source_model_version": "probability-calibration-v0",
      "stop": "figure_amplitude",
      "target": "full_retrace",
      "ticker": "ARM"
    },
    {
      "confidence": "low",
      "confirmation_lag": 1,
      "confirmed": true,
      "direction": "up",
      "end_idx": 1095,
      "end_ts": "2025-10-21 00:00:00",
      "entry_idx": 1096,
      "entry_ts": "2025-10-22 00:00:00",
      "entry_zone": "fade_after_confirmed_pattern",
      "expected_net_return": 0.04511299355282928,
      "interval": "1d",
      "lgbm_action": null,
      "lgbm_prob": null,
      "lgbm_threshold": null,
      "lookup_key": "flat|1d|short",
      "lookup_level": "fig_type+interval+side",
      "n_checks": 3,
      "n_errors": 0,
      "p_down": 0.6956521739130435,
      "p_trade_win": 0.6956521739130435,
      "p_up": 0.30434782608695654,
      "pattern": "flat",
      "recommended_action": "sell",
      "risk_box": {
        "amplitude": 11.459999084472656,
        "entry_px": 111.63700103759766,
        "stop_px": 123.09700012207031,
        "target_px": 100.177001953125
      },
      "sample_size": 23,
      "side": "short",
      "source_model_version": "probability-calibration-v0",
      "stop": "figure_amplitude",
      "target": "full_retrace",
      "ticker": "NFLX"
    },
    {
      "confidence": "low",
      "confirmation_lag": 2,
      "confirmed": true,
      "direction": "down",
      "end_idx": 1093,
      "end_ts": "2025-10-17 00:00:00",
      "entry_idx": 1095,
      "entry_ts": "2025-10-21 00:00:00",
      "entry_zone": "fade_after_confirmed_pattern",
      "expected_net_return": 0.021929896210771276,
      "interval": "1d",
      "lgbm_action": null,
      "lgbm_prob": null,
      "lgbm_threshold": null,
      "lookup_key": "flat|1d|long",
      "lookup_level": "fig_type+interval+side",
      "n_checks": 3,
      "n_errors": 0,
      "p_down": 0.33333333333333337,
      "p_trade_win": 0.6666666666666666,
      "p_up": 0.6666666666666666,
      "pattern": "flat",
      "recommended_action": "buy",
      "risk_box": {
        "amplitude": 34.229494679327956,
        "entry_px": 210.0279083251953,
        "stop_px": 175.79841364586736,
        "target_px": 244.25740300452327
      },
      "sample_size": 24,
      "side": "long",
      "source_model_version": "probability-calibration-v0",
      "stop": "figure_amplitude",
      "target": "full_retrace",
      "ticker": "BKNG"
    },
    {
      "confidence": "low",
      "confirmation_lag": 4,
      "confirmed": true,
      "direction": "up",
      "end_idx": 1084,
      "end_ts": "2025-10-06 00:00:00",
      "entry_idx": 1088,
      "entry_ts": "2025-10-10 00:00:00",
      "entry_zone": "fade_after_confirmed_pattern",
      "expected_net_return": 0.04511299355282928,
      "interval": "1d",
      "lgbm_action": null,
      "lgbm_prob": null,
      "lgbm_threshold": null,
      "lookup_key": "flat|1d|short",
      "lookup_level": "fig_type+interval+side",
      "n_checks": 3,
      "n_errors": 0,
      "p_down": 0.6956521739130435,
      "p_trade_win": 0.6956521739130435,
      "p_up": 0.30434782608695654,
      "pattern": "flat",
      "recommended_action": "sell",
      "risk_box": {
        "amplitude": 22.889984130859375,
        "entry_px": 429.5899963378906,
        "stop_px": 452.47998046875,
        "target_px": 406.70001220703125
      },
      "sample_size": 23,
      "side": "short",
      "source_model_version": "probability-calibration-v0",
      "stop": "figure_amplitude",
      "target": "full_retrace",
      "ticker": "ISRG"
    },
    {
      "confidence": "low",
      "confirmation_lag": 5,
      "confirmed": true,
      "direction": "down",
      "end_idx": 1567,
      "end_ts": "2025-09-26 00:00:00+00:00",
      "entry_idx": 1572,
      "entry_ts": "2025-10-01 00:00:00+00:00",
      "entry_zone": "fade_after_confirmed_pattern",
      "expected_net_return": 0.021929896210771276,
      "interval": "1d",
      "lgbm_action": null,
      "lgbm_prob": null,
      "lgbm_threshold": null,
      "lookup_key": "flat|1d|long",
      "lookup_level": "fig_type+interval+side",
      "n_checks": 3,
      "n_errors": 0,
      "p_down": 0.33333333333333337,
      "p_trade_win": 0.6666666666666666,
      "p_up": 0.6666666666666666,
      "pattern": "flat",
      "recommended_action": "buy",
      "risk_box": {
        "amplitude": 19.060000000000002,
        "entry_px": 222.04,
        "stop_px": 202.98,
        "target_px": 241.1
      },
      "sample_size": 24,
      "side": "long",
      "source_model_version": "probability-calibration-v0",
      "stop": "figure_amplitude",
      "target": "full_retrace",
      "ticker": "SOL-USD"
    },
    {
      "confidence": "low",
      "confirmation_lag": 3,
      "confirmed": true,
      "direction": "down",
      "end_idx": 1567,
      "end_ts": "2025-09-26 00:00:00+00:00",
      "entry_idx": 1570,
      "entry_ts": "2025-09-29 00:00:00+00:00",
      "entry_zone": "fade_after_confirmed_pattern",
      "expected_net_return": 0.021929896210771276,
      "interval": "1d",
      "lgbm_action": null,
      "lgbm_prob": null,
      "lgbm_threshold": null,
      "lookup_key": "flat|1d|long",
      "lookup_level": "fig_type+interval+side",
      "n_checks": 3,
      "n_errors": 0,
      "p_down": 0.33333333333333337,
      "p_trade_win": 0.6666666666666666,
      "p_up": 0.6666666666666666,
      "pattern": "flat",
      "recommended_action": "buy",
      "risk_box": {
        "amplitude": 70.90999999999997,
        "entry_px": 1029.79,
        "stop_px": 958.88,
        "target_px": 1100.6999999999998
      },
      "sample_size": 24,
      "side": "long",
      "source_model_version": "probability-calibration-v0",
      "stop": "figure_amplitude",
      "target": "full_retrace",
      "ticker": "BNB-USD"
    },
    {
      "confidence": "low",
      "confirmation_lag": 12,
      "confirmed": true,
      "direction": "up",
      "end_idx": 1554,
      "end_ts": "2025-09-13 00:00:00+00:00",
      "entry_idx": 1566,
      "entry_ts": "2025-09-25 00:00:00+00:00",
      "entry_zone": "fade_after_confirmed_pattern",
      "expected_net_return": 0.04511299355282928,
      "interval": "1d",
      "lgbm_action": null,
      "lgbm_prob": null,
      "lgbm_threshold": null,
      "lookup_key": "flat|1d|short",
      "lookup_level": "fig_type+interval+side",
      "n_checks": 3,
      "n_errors": 0,
      "p_down": 0.6956521739130435,
      "p_trade_win": 0.6956521739130435,
      "p_up": 0.30434782608695654,
      "pattern": "flat",
      "recommended_action": "sell",
      "risk_box": {
        "amplitude": 0.010300000000000031,
        "entry_px": 0.3319,
        "stop_px": 0.3422,
        "target_px": 0.32159999999999994
      },
      "sample_size": 23,
      "side": "short",
      "source_model_version": "probability-calibration-v0",
      "stop": "figure_amplitude",
      "target": "full_retrace",
      "ticker": "TRX-USD"
    },
    {
      "confidence": "low",
      "confirmation_lag": 3,
      "confirmed": true,
      "direction": "up",
      "end_idx": 1206,
      "end_ts": "2025-09-19 00:00:00+00:00",
      "entry_idx": 1209,
      "entry_ts": "2025-09-22 00:00:00+00:00",
      "entry_zone": "fade_after_confirmed_pattern",
      "expected_net_return": 0.04511299355282928,
      "interval": "1d",
      "lgbm_action": null,
      "lgbm_prob": null,
      "lgbm_threshold": null,
      "lookup_key": "flat|1d|short",
      "lookup_level": "fig_type+interval+side",
      "n_checks": 3,
      "n_errors": 0,
      "p_down": 0.6956521739130435,
      "p_trade_win": 0.6956521739130435,
      "p_up": 0.30434782608695654,
      "pattern": "flat",
      "recommended_action": "sell",
      "risk_box": {
        "amplitude": 0.242,
        "entry_px": 0.7036,
        "stop_px": 0.9456,
        "target_px": 0.4616
      },
      "sample_size": 23,
      "side": "short",
      "source_model_version": "probability-calibration-v0",
      "stop": "figure_amplitude",
      "target": "full_retrace",
      "ticker": "OP-USD"
    },
    {
      "confidence": "low",
      "confirmation_lag": 11,
      "confirmed": true,
      "direction": "up",
      "end_idx": 1534,
      "end_ts": "2025-08-24 00:00:00+00:00",
      "entry_idx": 1545,
      "entry_ts": "2025-09-04 00:00:00+00:00",
      "entry_zone": "fade_after_confirmed_pattern",
      "expected_net_return": 0.04511299355282928,
      "interval": "1d",
      "lgbm_action": null,
      "lgbm_prob": null,
      "lgbm_threshold": null,
      "lookup_key": "flat|1d|short",
      "lookup_level": "fig_type+interval+side",
      "n_checks": 3,
      "n_errors": 0,
      "p_down": 0.6956521739130435,
      "p_trade_win": 0.6956521739130435,
      "p_up": 0.30434782608695654,
      "pattern": "flat",
      "recommended_action": "sell",
      "risk_box": {
        "amplitude": 0.9640000000000004,
        "entry_px": 4.386,
        "stop_px": 5.3500000000000005,
        "target_px": 3.4219999999999997
      },
      "sample_size": 23,
      "side": "short",
      "source_model_version": "probability-calibration-v0",
      "stop": "figure_amplitude",
      "target": "full_retrace",
      "ticker": "ATOM-USD"
    },
    {
      "confidence": "low",
      "confirmation_lag": 6,
      "confirmed": true,
      "direction": "down",
      "end_idx": 1039,
      "end_ts": "2025-08-01 00:00:00",
      "entry_idx": 1045,
      "entry_ts": "2025-08-11 00:00:00",
      "entry_zone": "fade_after_confirmed_pattern",
      "expected_net_return": 0.021929896210771276,
      "interval": "1d",
      "lgbm_action": null,
      "lgbm_prob": null,
      "lgbm_threshold": null,
      "lookup_key": "flat|1d|long",
      "lookup_level": "fig_type+interval+side",
      "n_checks": 3,
      "n_errors": 0,
      "p_down": 0.33333333333333337,
      "p_trade_win": 0.6666666666666666,
      "p_up": 0.6666666666666666,
      "pattern": "flat",
      "recommended_action": "buy",
      "risk_box": {
        "amplitude": 111.16511525849626,
        "entry_px": 717.516845703125,
        "stop_px": 606.3517304446287,
        "target_px": 828.6819609616213
      },
      "sample_size": 24,
      "side": "long",
      "source_model_version": "probability-calibration-v0",
      "stop": "figure_amplitude",
      "target": "full_retrace",
      "ticker": "ASML"
    },
    {
      "confidence": "low",
      "confirmation_lag": 5,
      "confirmed": true,
      "direction": "up",
      "end_idx": 1038,
      "end_ts": "2025-07-31 00:00:00",
      "entry_idx": 1043,
      "entry_ts": "2025-08-07 00:00:00",
      "entry_zone": "fade_after_confirmed_pattern",
      "expected_net_return": 0.04511299355282928,
      "interval": "1d",
      "lgbm_action": null,
      "lgbm_prob": null,
      "lgbm_threshold": null,
      "lookup_key": "flat|1d|short",
      "lookup_level": "fig_type+interval+side",
      "n_checks": 3,
      "n_errors": 0,
      "p_down": 0.6956521739130435,
      "p_trade_win": 0.6956521739130435,
      "p_up": 0.30434782608695654,
      "pattern": "flat",
      "recommended_action": "sell",
      "risk_box": {
        "amplitude": 124.26817995929503,
        "entry_px": 414.1656494140625,
        "stop_px": 538.4338293733575,
        "target_px": 289.8974694547675
      },
      "sample_size": 23,
      "side": "short",
      "source_model_version": "probability-calibration-v0",
      "stop": "figure_amplitude",
      "target": "full_retrace",
      "ticker": "CAT"
    },
    {
      "confidence": "low",
      "confirmation_lag": 1,
      "confirmed": true,
      "direction": "down",
      "end_idx": 1490,
      "end_ts": "2025-07-11 00:00:00+00:00",
      "entry_idx": 1491,
      "entry_ts": "2025-07-12 00:00:00+00:00",
      "entry_zone": "fade_after_confirmed_pattern",
      "expected_net_return": 0.021929896210771276,
      "interval": "1d",
      "lgbm_action": null,
      "lgbm_prob": null,
      "lgbm_threshold": null,
      "lookup_key": "flat|1d|long",
      "lookup_level": "fig_type+interval+side",
      "n_checks": 3,
      "n_errors": 0,
      "p_down": 0.33333333333333337,
      "p_trade_win": 0.6666666666666666,
      "p_up": 0.6666666666666666,
      "pattern": "flat",
      "recommended_action": "buy",
      "risk_box": {
        "amplitude": 0.0,
        "entry_px": 0.3929,
        "stop_px": null,
        "target_px": null
      },
      "sample_size": 24,
      "side": "long",
      "source_model_version": "probability-calibration-v0",
      "stop": "figure_amplitude",
      "target": "full_retrace",
      "ticker": "XLM-USD"
    },
    {
      "confidence": "low",
      "confirmation_lag": 0,
      "confirmed": true,
      "direction": "up",
      "end_idx": 1490,
      "end_ts": "2025-07-11 00:00:00+00:00",
      "entry_idx": 1490,
      "entry_ts": "2025-07-11 00:00:00+00:00",
      "entry_zone": "fade_after_confirmed_pattern",
      "expected_net_return": 0.04511299355282928,
      "interval": "1d",
      "lgbm_action": null,
      "lgbm_prob": null,
      "lgbm_threshold": null,
      "lookup_key": "flat|1d|short",
      "lookup_level": "fig_type+interval+side",
      "n_checks": 3,
      "n_errors": 0,
      "p_down": 0.6956521739130435,
      "p_trade_win": 0.6956521739130435,
      "p_up": 0.30434782608695654,
      "pattern": "flat",
      "recommended_action": "sell",
      "risk_box": {
        "amplitude": 0.15879999999999994,
        "entry_px": 0.7094,
        "stop_px": 0.8682,
        "target_px": 0.5506000000000001
      },
      "sample_size": 23,
      "side": "short",
      "source_model_version": "probability-calibration-v0",
      "stop": "figure_amplitude",
      "target": "full_retrace",
      "ticker": "ADA-USD"
    },
    {
      "confidence": "low",
      "confirmation_lag": 4,
      "confirmed": true,
      "direction": "down",
      "end_idx": 1471,
      "end_ts": "2025-06-22 00:00:00+00:00",
      "entry_idx": 1475,
      "entry_ts": "2025-06-26 00:00:00+00:00",
      "entry_zone": "fade_after_confirmed_pattern",
      "expected_net_return": 0.021929896210771276,
      "interval": "1d",
      "lgbm_action": null,
      "lgbm_prob": null,
      "lgbm_threshold": null,
      "lookup_key": "flat|1d|long",
      "lookup_level": "fig_type+interval+side",
      "n_checks": 3,
      "n_errors": 0,
      "p_down": 0.33333333333333337,
      "p_trade_win": 0.6666666666666666,
      "p_up": 0.6666666666666666,
      "pattern": "flat",
      "recommended_action": "buy",
      "risk_box": {
        "amplitude": 676.1100000000001,
        "entry_px": 2415.96,
        "stop_px": 1739.85,
        "target_px": 3092.07
      },
      "sample_size": 24,
      "side": "long",
      "source_model_version": "probability-calibration-v0",
      "stop": "figure_amplitude",
      "target": "full_retrace",
      "ticker": "ETH-USD"
    },
    {
      "confidence": "low",
      "confirmation_lag": 2,
      "confirmed": true,
      "direction": "down",
      "end_idx": 1471,
      "end_ts": "2025-06-22 00:00:00+00:00",
      "entry_idx": 1473,
      "entry_ts": "2025-06-24 00:00:00+00:00",
      "entry_zone": "fade_after_confirmed_pattern",
      "expected_net_return": 0.0878223332967692,
      "interval": "1d",
      "lgbm_action": null,
      "lgbm_prob": null,
      "lgbm_threshold": null,
      "lookup_key": "double_corr|1d|long",
      "lookup_level": "fig_type+interval+side",
      "n_checks": 1,
      "n_errors": 0,
      "p_down": 0.0,
      "p_trade_win": 1.0,
      "p_up": 1.0,
      "pattern": "double_corr",
      "recommended_action": "buy",
      "risk_box": {
        "amplitude": 7.040000000000001,
        "entry_px": 13.42,
        "stop_px": 6.379999999999999,
        "target_px": 20.46
      },
      "sample_size": 3,
      "side": "long",
      "source_model_version": "probability-calibration-v0",
      "stop": "figure_amplitude",
      "target": "full_retrace",
      "ticker": "LINK-USD"
    },
    {
      "confidence": "low",
      "confirmation_lag": 2,
      "confirmed": true,
      "direction": "up",
      "end_idx": 1106,
      "end_ts": "2025-06-11 00:00:00+00:00",
      "entry_idx": 1108,
      "entry_ts": "2025-06-13 00:00:00+00:00",
      "entry_zone": "fade_after_confirmed_pattern",
      "expected_net_return": 0.04511299355282928,
      "interval": "1d",
      "lgbm_action": null,
      "lgbm_prob": null,
      "lgbm_threshold": null,
      "lookup_key": "flat|1d|short",
      "lookup_level": "fig_type+interval+side",
      "n_checks": 3,
      "n_errors": 0,
      "p_down": 0.6956521739130435,
      "p_trade_win": 0.6956521739130435,
      "p_up": 0.30434782608695654,
      "pattern": "flat",
      "recommended_action": "sell",
      "risk_box": {
        "amplitude": 0.0010000000000000009,
        "entry_px": 0.591,
        "stop_px": 0.592,
        "target_px": 0.59
      },
      "sample_size": 23,
      "side": "short",
      "source_model_version": "probability-calibration-v0",
      "stop": "figure_amplitude",
      "target": "full_retrace",
      "ticker": "OP-USD"
    },
    {
      "confidence": "low",
      "confirmation_lag": 21,
      "confirmed": true,
      "direction": "up",
      "end_idx": 985,
      "end_ts": "2025-05-14 00:00:00",
      "entry_idx": 1006,
      "entry_ts": "2025-06-13 00:00:00",
      "entry_zone": "fade_after_confirmed_pattern",
      "expected_net_return": 0.04511299355282928,
      "interval": "1d",
      "lgbm_action": null,
      "lgbm_prob": null,
      "lgbm_threshold": null,
      "lookup_key": "flat|1d|short",
      "lookup_level": "fig_type+interval+side",
      "n_checks": 3,
      "n_errors": 0,
      "p_down": 0.6956521739130435,
      "p_trade_win": 0.6956521739130435,
      "p_up": 0.30434782608695654,
      "pattern": "flat",
      "recommended_action": "sell",
      "risk_box": {
        "amplitude": 53.61799621582031,
        "entry_px": 197.73199462890625,
        "stop_px": 251.34999084472656,
        "target_px": 144.11399841308594
      },
      "sample_size": 23,
      "side": "short",
      "source_model_version": "probability-calibration-v0",
      "stop": "figure_amplitude",
      "target": "full_retrace",
      "ticker": "NOW"
    },
    {
      "confidence": "low",
      "confirmation_lag": 6,
      "confirmed": true,
      "direction": "down",
      "end_idx": 1454,
      "end_ts": "2025-06-05 00:00:00+00:00",
      "entry_idx": 1460,
      "entry_ts": "2025-06-11 00:00:00+00:00",
      "entry_zone": "fade_after_confirmed_pattern",
      "expected_net_return": 0.021929896210771276,
      "interval": "1d",
      "lgbm_action": null,
      "lgbm_prob": null,
      "lgbm_threshold": null,
      "lookup_key": "flat|1d|long",
      "lookup_level": "fig_type+interval+side",
      "n_checks": 3,
      "n_errors": 0,
      "p_down": 0.33333333333333337,
      "p_trade_win": 0.6666666666666666,
      "p_up": 0.6666666666666666,
      "pattern": "flat",
      "recommended_action": "buy",
      "risk_box": {
        "amplitude": 0.6319999999999997,
        "entry_px": 4.189,
        "stop_px": 3.5570000000000004,
        "target_px": 4.821
      },
      "sample_size": 24,
      "side": "long",
      "source_model_version": "probability-calibration-v0",
      "stop": "figure_amplitude",
      "target": "full_retrace",
      "ticker": "DOT-USD"
    },
    {
      "confidence": "low",
      "confirmation_lag": 6,
      "confirmed": true,
      "direction": "down",
      "end_idx": 1454,
      "end_ts": "2025-06-05 00:00:00+00:00",
      "entry_idx": 1460,
      "entry_ts": "2025-06-11 00:00:00+00:00",
      "entry_zone": "fade_after_confirmed_pattern",
      "expected_net_return": 0.021929896210771276,
      "interval": "1d",
      "lgbm_action": null,
      "lgbm_prob": null,
      "lgbm_threshold": null,
      "lookup_key": "flat|1d|long",
      "lookup_level": "fig_type+interval+side",
      "n_checks": 3,
      "n_errors": 0,
      "p_down": 0.33333333333333337,
      "p_trade_win": 0.6666666666666666,
      "p_up": 0.6666666666666666,
      "pattern": "flat",
      "recommended_action": "buy",
      "risk_box": {
        "amplitude": 0.5049999999999999,
        "entry_px": 2.573,
        "stop_px": 2.068,
        "target_px": 3.078
      },
      "sample_size": 24,
      "side": "long",
      "source_model_version": "probability-calibration-v0",
      "stop": "figure_amplitude",
      "target": "full_retrace",
      "ticker": "NEAR-USD"
    },
    {
      "confidence": "low",
      "confirmation_lag": 1,
      "confirmed": true,
      "direction": "down",
      "end_idx": 959,
      "end_ts": "2025-04-07 00:00:00",
      "entry_idx": 960,
      "entry_ts": "2025-04-08 00:00:00",
      "entry_zone": "fade_after_confirmed_pattern",
      "expected_net_return": 0.0878223332967692,
      "interval": "1d",
      "lgbm_action": null,
      "lgbm_prob": null,
      "lgbm_threshold": null,
      "lookup_key": "double_corr|1d|long",
      "lookup_level": "fig_type+interval+side",
      "n_checks": 1,
      "n_errors": 0,
      "p_down": 0.0,
      "p_trade_win": 1.0,
      "p_up": 1.0,
      "pattern": "double_corr",
      "recommended_action": "buy",
      "risk_box": {
        "amplitude": 56.7273164025905,
        "entry_px": 96.16523742675781,
        "stop_px": 39.43792102416731,
        "target_px": 152.89255382934832
      },
      "sample_size": 3,
      "side": "long",
      "source_model_version": "probability-calibration-v0",
      "stop": "figure_amplitude",
      "target": "full_retrace",
      "ticker": "NVDA"
    },
    {
      "confidence": "low",
      "confirmation_lag": 2,
      "confirmed": true,
      "direction": "up",
      "end_idx": 952,
      "end_ts": "2025-03-27 00:00:00",
      "entry_idx": 954,
      "entry_ts": "2025-03-31 00:00:00",
      "entry_zone": "fade_after_confirmed_pattern",
      "expected_net_return": 0.04511299355282928,
      "interval": "1d",
      "lgbm_action": null,
      "lgbm_prob": null,
      "lgbm_threshold": null,
      "lookup_key": "flat|1d|short",
      "lookup_level": "fig_type+interval+side",
      "n_checks": 3,
      "n_errors": 0,
      "p_down": 0.6956521739130435,
      "p_trade_win": 0.6956521739130435,
      "p_up": 0.30434782608695654,
      "pattern": "flat",
      "recommended_action": "sell",
      "risk_box": {
        "amplitude": 10.679923043039366,
        "entry_px": 544.0384521484375,
        "stop_px": 554.7183751914769,
        "target_px": 533.3585291053981
      },
      "sample_size": 23,
      "side": "short",
      "source_model_version": "probability-calibration-v0",
      "stop": "figure_amplitude",
      "target": "full_retrace",
      "ticker": "MA"
    },
    {
      "confidence": "low",
      "confirmation_lag": 4,
      "confirmed": true,
      "direction": "up",
      "end_idx": 949,
      "end_ts": "2025-03-24 00:00:00",
      "entry_idx": 953,
      "entry_ts": "2025-03-28 00:00:00",
      "entry_zone": "fade_after_confirmed_pattern",
      "expected_net_return": 0.04511299355282928,
      "interval": "1d",
      "lgbm_action": null,
      "lgbm_prob": null,
      "lgbm_threshold": null,
      "lookup_key": "flat|1d|short",
      "lookup_level": "fig_type+interval+side",
      "n_checks": 3,
      "n_errors": 0,
      "p_down": 0.6956521739130435,
      "p_trade_win": 0.6956521739130435,
      "p_up": 0.30434782608695654,
      "pattern": "flat",
      "recommended_action": "sell",
      "risk_box": {
        "amplitude": 3.8869055099282264,
        "entry_px": 138.97146606445312,
        "stop_px": 142.85837157438135,
        "target_px": 135.0845605545249
      },
      "sample_size": 23,
      "side": "short",
      "source_model_version": "probability-calibration-v0",
      "stop": "figure_amplitude",
      "target": "full_retrace",
      "ticker": "ORCL"
    },
    {
      "confidence": "low",
      "confirmation_lag": 2,
      "confirmed": true,
      "direction": "up",
      "end_idx": 911,
      "end_ts": "2025-01-28 00:00:00",
      "entry_idx": 913,
      "entry_ts": "2025-01-30 00:00:00",
      "entry_zone": "fade_after_confirmed_pattern",
      "expected_net_return": 0.04511299355282928,
      "interval": "1d",
      "lgbm_action": null,
      "lgbm_prob": null,
      "lgbm_threshold": null,
      "lookup_key": "flat|1d|short",
      "lookup_level": "fig_type+interval+side",
      "n_checks": 3,
      "n_errors": 0,
      "p_down": 0.6956521739130435,
      "p_trade_win": 0.6956521739130435,
      "p_up": 0.30434782608695654,
      "pattern": "flat",
      "recommended_action": "sell",
      "risk_box": {
        "amplitude": 37.21853760506457,
        "entry_px": 410.12469482421875,
        "stop_px": 447.3432324292833,
        "target_px": 372.9061572191542
      },
      "sample_size": 23,
      "side": "short",
      "source_model_version": "probability-calibration-v0",
      "stop": "figure_amplitude",
      "target": "full_retrace",
      "ticker": "MSFT"
    },
    {
      "confidence": "low",
      "confirmation_lag": 2,
      "confirmed": true,
      "direction": "down",
      "end_idx": 1311,
      "end_ts": "2025-01-13 00:00:00+00:00",
      "entry_idx": 1313,
      "entry_ts": "2025-01-15 00:00:00+00:00",
      "entry_zone": "fade_after_confirmed_pattern",
      "expected_net_return": 0.021929896210771276,
      "interval": "1d",
      "lgbm_action": null,
      "lgbm_prob": null,
      "lgbm_threshold": null,
      "lookup_key": "flat|1d|long",
      "lookup_level": "fig_type+interval+side",
      "n_checks": 3,
      "n_errors": 0,
      "p_down": 0.33333333333333337,
      "p_trade_win": 0.6666666666666666,
      "p_up": 0.6666666666666666,
      "pattern": "flat",
      "recommended_action": "buy",
      "risk_box": {
        "amplitude": 1187.8000000000002,
        "entry_px": 3451.52,
        "stop_px": 2263.72,
        "target_px": 4639.32
      },
      "sample_size": 24,
      "side": "long",
      "source_model_version": "probability-calibration-v0",
      "stop": "figure_amplitude",
      "target": "full_retrace",
      "ticker": "ETH-USD"
    },
    {
      "confidence": "low",
      "confirmation_lag": 14,
      "confirmed": true,
      "direction": "down",
      "end_idx": 1287,
      "end_ts": "2024-12-20 00:00:00+00:00",
      "entry_idx": 1301,
      "entry_ts": "2025-01-03 00:00:00+00:00",
      "entry_zone": "fade_after_confirmed_pattern",
      "expected_net_return": 0.021929896210771276,
      "interval": "1d",
      "lgbm_action": null,
      "lgbm_prob": null,
      "lgbm_threshold": null,
      "lookup_key": "flat|1d|long",
      "lookup_level": "fig_type+interval+side",
      "n_checks": 3,
      "n_errors": 0,
      "p_down": 0.33333333333333337,
      "p_trade_win": 0.6666666666666666,
      "p_up": 0.6666666666666666,
      "pattern": "flat",
      "recommended_action": "buy",
      "risk_box": {
        "amplitude": 4.49,
        "entry_px": 7.754,
        "stop_px": 3.2639999999999993,
        "target_px": 12.244
      },
      "sample_size": 24,
      "side": "long",
      "source_model_version": "probability-calibration-v0",
      "stop": "figure_amplitude",
      "target": "full_retrace",
      "ticker": "DOT-USD"
    },
    {
      "confidence": "low",
      "confirmation_lag": 2,
      "confirmed": true,
      "direction": "up",
      "end_idx": 884,
      "end_ts": "2024-12-16 00:00:00",
      "entry_idx": 886,
      "entry_ts": "2024-12-18 00:00:00",
      "entry_zone": "fade_after_confirmed_pattern",
      "expected_net_return": 0.04511299355282928,
      "interval": "1d",
      "lgbm_action": null,
      "lgbm_prob": null,
      "lgbm_threshold": null,
      "lookup_key": "flat|1d|short",
      "lookup_level": "fig_type+interval+side",
      "n_checks": 3,
      "n_errors": 0,
      "p_down": 0.6956521739130435,
      "p_trade_win": 0.6956521739130435,
      "p_up": 0.30434782608695654,
      "pattern": "flat",
      "recommended_action": "sell",
      "risk_box": {
        "amplitude": 83.34466324826795,
        "entry_px": 220.5625,
        "stop_px": 303.9071632482679,
        "target_px": 137.21783675173205
      },
      "sample_size": 23,
      "side": "short",
      "source_model_version": "probability-calibration-v0",
      "stop": "figure_amplitude",
      "target": "full_retrace",
      "ticker": "AVGO"
    },
    {
      "confidence": "low",
      "confirmation_lag": 1,
      "confirmed": true,
      "direction": "up",
      "end_idx": 1250,
      "end_ts": "2024-11-13 00:00:00+00:00",
      "entry_idx": 1251,
      "entry_ts": "2024-11-14 00:00:00+00:00",
      "entry_zone": "fade_after_confirmed_pattern",
      "expected_net_return": 0.04511299355282928,
      "interval": "1d",
      "lgbm_action": null,
      "lgbm_prob": null,
      "lgbm_threshold": null,
      "lookup_key": "flat|1d|short",
      "lookup_level": "fig_type+interval+side",
      "n_checks": 3,
      "n_errors": 0,
      "p_down": 0.6956521739130435,
      "p_trade_win": 0.6956521739130435,
      "p_up": 0.30434782608695654,
      "pattern": "flat",
      "recommended_action": "sell",
      "risk_box": {
        "amplitude": 0.03260000000000002,
        "entry_px": 0.1765,
        "stop_px": 0.2091,
        "target_px": 0.14389999999999997
      },
      "sample_size": 23,
      "side": "short",
      "source_model_version": "probability-calibration-v0",
      "stop": "figure_amplitude",
      "target": "full_retrace",
      "ticker": "TRX-USD"
    },
    {
      "confidence": "low",
      "confirmation_lag": 1,
      "confirmed": true,
      "direction": "down",
      "end_idx": 1249,
      "end_ts": "2024-11-12 00:00:00+00:00",
      "entry_idx": 1250,
      "entry_ts": "2024-11-13 00:00:00+00:00",
      "entry_zone": "fade_after_confirmed_pattern",
      "expected_net_return": 0.021929896210771276,
      "interval": "1d",
      "lgbm_action": null,
      "lgbm_prob": null,
      "lgbm_threshold": null,
      "lookup_key": "flat|1d|long",
      "lookup_level": "fig_type+interval+side",
      "n_checks": 3,
      "n_errors": 0,
      "p_down": 0.33333333333333337,
      "p_trade_win": 0.6666666666666666,
      "p_up": 0.6666666666666666,
      "pattern": "flat",
      "recommended_action": "buy",
      "risk_box": {
        "amplitude": 0.02190000000000003,
        "entry_px": 0.6898,
        "stop_px": 0.6678999999999999,
        "target_px": 0.7117
      },
      "sample_size": 24,
      "side": "long",
      "source_model_version": "probability-calibration-v0",
      "stop": "figure_amplitude",
      "target": "full_retrace",
      "ticker": "XRP-USD"
    },
    {
      "confidence": "low",
      "confirmation_lag": 1,
      "confirmed": true,
      "direction": "down",
      "end_idx": 1247,
      "end_ts": "2024-11-10 00:00:00+00:00",
      "entry_idx": 1248,
      "entry_ts": "2024-11-11 00:00:00+00:00",
      "entry_zone": "fade_after_confirmed_pattern",
      "expected_net_return": 0.021929896210771276,
      "interval": "1d",
      "lgbm_action": null,
      "lgbm_prob": null,
      "lgbm_threshold": null,
      "lookup_key": "flat|1d|long",
      "lookup_level": "fig_type+interval+side",
      "n_checks": 3,
      "n_errors": 0,
      "p_down": 0.33333333333333337,
      "p_trade_win": 0.6666666666666666,
      "p_up": 0.6666666666666666,
      "pattern": "flat",
      "recommended_action": "buy",
      "risk_box": {
        "amplitude": 0.03300000000000036,
        "entry_px": 5.71,
        "stop_px": 5.677,
        "target_px": 5.743
      },
      "sample_size": 24,
      "side": "long",
      "source_model_version": "probability-calibration-v0",
      "stop": "figure_amplitude",
      "target": "full_retrace",
      "ticker": "DOT-USD"
    },
    {
      "confidence": "low",
      "confirmation_lag": 2,
      "confirmed": true,
      "direction": "down",
      "end_idx": 1241,
      "end_ts": "2024-11-04 00:00:00+00:00",
      "entry_idx": 1243,
      "entry_ts": "2024-11-06 00:00:00+00:00",
      "entry_zone": "fade_after_confirmed_pattern",
      "expected_net_return": 0.021929896210771276,
      "interval": "1d",
      "lgbm_action": null,
      "lgbm_prob": null,
      "lgbm_threshold": null,
      "lookup_key": "flat|1d|long",
      "lookup_level": "fig_type+interval+side",
      "n_checks": 3,
      "n_errors": 0,
      "p_down": 0.33333333333333337,
      "p_trade_win": 0.6666666666666666,
      "p_up": 0.6666666666666666,
      "pattern": "flat",
      "recommended_action": "buy",
      "risk_box": {
        "amplitude": 8.5,
        "entry_px": 27.01,
        "stop_px": 18.51,
        "target_px": 35.510000000000005
      },
      "sample_size": 24,
      "side": "long",
      "source_model_version": "probability-calibration-v0",
      "stop": "figure_amplitude",
      "target": "full_retrace",
      "ticker": "AVAX-USD"
    },
    {
      "confidence": "low",
      "confirmation_lag": 2,
      "confirmed": true,
      "direction": "down",
      "end_idx": 887,
      "end_ts": "2024-11-04 00:00:00+00:00",
      "entry_idx": 889,
      "entry_ts": "2024-11-06 00:00:00+00:00",
      "entry_zone": "fade_after_confirmed_pattern",
      "expected_net_return": 0.021929896210771276,
      "interval": "1d",
      "lgbm_action": null,
      "lgbm_prob": null,
      "lgbm_threshold": null,
      "lookup_key": "flat|1d|long",
      "lookup_level": "fig_type+interval+side",
      "n_checks": 3,
      "n_errors": 0,
      "p_down": 0.33333333333333337,
      "p_trade_win": 0.6666666666666666,
      "p_up": 0.6666666666666666,
      "pattern": "flat",
      "recommended_action": "buy",
      "risk_box": {
        "amplitude": 0.536,
        "entry_px": 1.601,
        "stop_px": 1.065,
        "target_px": 2.137
      },
      "sample_size": 24,
      "side": "long",
      "source_model_version": "probability-calibration-v0",
      "stop": "figure_amplitude",
      "target": "full_retrace",
      "ticker": "OP-USD"
    }
  ],
  "tickers": [
    "NVDA",
    "AVGO",
    "AMD",
    "TSM",
    "ASML",
    "ARM",
    "MU",
    "MSFT",
    "ORCL",
    "CRM",
    "NOW",
    "PLTR",
    "CRWD",
    "PANW",
    "SNOW",
    "AMZN",
    "GOOGL",
    "META",
    "NFLX",
    "UBER",
    "SHOP",
    "BKNG",
    "LLY",
    "NVO",
    "ISRG",
    "VRTX",
    "TSLA",
    "V",
    "MA",
    "CAT",
    "BTC-USD",
    "ETH-USD",
    "BNB-USD",
    "SOL-USD",
    "XRP-USD",
    "DOGE-USD",
    "ADA-USD",
    "AVAX-USD",
    "TRX-USD",
    "LINK-USD",
    "DOT-USD",
    "LTC-USD",
    "ATOM-USD",
    "XLM-USD",
    "OP-USD",
    "NEAR-USD",
    "HBAR-USD",
    "FIL-USD",
    "INJ-USD",
    "AAVE-USD"
  ]
}
